reqs_sync/__init__.py
reqs_sync/__main__.py
reqs_sync/cli.py
reqs_sync/r2toml.py
reqs_sync-0.1.dist-info/LICENSE
reqs_sync-0.1.dist-info/METADATA
reqs_sync-0.1.dist-info/WHEEL
reqs_sync-0.1.dist-info/entry_points.txt
reqs_sync-0.1.dist-info/top_level.txt
reqs_sync-0.1.dist-info/RECORD
