Metadata-Version: 2.1
Name: reqs-sync
Version: 0.1
Summary: null
Author: saaspegasus
License: Apache-2.0
Project-URL: Homepage, https://github.com/saaspegasus/reqs-sync
Project-URL: Changelog, https://github.com/saaspegasus/reqs-sync/releases
Project-URL: Issues, https://github.com/saaspegasus/reqs-sync/issues
Project-URL: CI, https://github.com/saaspegasus/reqs-sync/actions
Classifier: License :: OSI Approved :: Apache Software License
Requires-Python: >=3.8
License-File: LICENSE
Requires-Dist: click
Requires-Dist: tomlkit
